{"formatVersion": "0.0.12", "routes": [{"summary": {"lengthInMeters": 51652, "travelTimeInSeconds": 4345, "trafficDelayInSeconds": 0, "trafficLengthInMeters": 0, "departureTime": "2026-05-30T16:50:02+02:00", "arrivalTime": "2026-05-30T18:02:27+02:00"}, "legs": [{"summary": {"lengthInMeters": 51652, "travelTimeInSeconds": 4345, "trafficDelayInSeconds": 0, "trafficLengthInMeters": 0, "departureTime": "2026-05-30T16:50:02+02:00", "arrivalTime": "2026-05-30T18:02:27+02:00"}, "points": [{"latitude": 48.85689, "longitude": 2.35085}, {"latitude": 48.85706, "longitude": 2.35029}, {"latitude": 48.85712, "longitude": 2.35008}, {"latitude": 48.8572, "longitude": 2.3498}, {"latitude": 48.85723, "longitude": 2.34967}, {"latitude": 48.85732, "longitude": 2.34929}, {"latitude": 48.85737, "longitude": 2.34909}, {"latitude": 48.85739, "longitude": 2.34901}, {"latitude": 48.8575, "longitude": 2.3486}, {"latitude": 48.85768, "longitude": 2.34794}, {"latitude": 48.85772, "longitude": 2.34777}, {"latitude": 48.85818, "longitude": 2.34803}, {"latitude": 48.85846, "longitude": 2.34819}, {"latitude": 48.85852, "longitude": 2.34823}, {"latitude": 48.85859, "longitude": 2.34827}, {"latitude": 48.85872, "longitude": 2.34833}, {"latitude": 48.85905, "longitude": 2.34852}, {"latitude": 48.85952, "longitude": 2.34878}, {"latitude": 48.86007, "longitude": 2.34908}, {"latitude": 48.86054, "longitude": 2.3494}, {"latitude": 48.86057, "longitude": 2.34942}, {"latitude": 48.86087, "longitude": 2.34958}, {"latitude": 48.86115, "longitude": 2.34975}, {"latitude": 48.86151, "longitude": 2.34993}, {"latitude": 48.86199, "longitude": 2.35018}, {"latitude": 48.86245, "longitude": 2.35043}, {"latitude": 48.86293, "longitude": 2.3507}, {"latitude": 48.86339, "longitude": 2.35095}, {"latitude": 48.8636, "longitude": 2.35107}, {"latitude": 48.86416, "longitude": 2.3514}, {"latitude": 48.86444, "longitude": 2.35155}, {"latitude": 48.86461, "longitude": 2.35165}, {"latitude": 48.86524, "longitude": 2.35198}, {"latitude": 48.86623, "longitude": 2.35254}, {"latitude": 48.86703, "longitude": 2.353}, {"latitude": 48.86719, "longitude": 2.35308}, {"latitude": 48.86741, "longitude": 2.3532}, {"latitude": 48.86762, "longitude": 2.35333}, {"latitude": 48.86789, "longitude": 2.35347}, {"latitude": 48.86818, "longitude": 2.35364}, {"latitude": 48.86836, "longitude": 2.35374}, {"latitude": 48.86867, "longitude": 2.35391}, {"latitude": 48.86891, "longitude": 2.35405}, {"latitude": 48.86907, "longitude": 2.35415}, {"latitude": 48.86931, "longitude": 2.35428}, {"latitude": 48.86957, "longitude": 2.35439}, {"latitude": 48.87059, "longitude": 2.35496}, {"latitude": 48.87103, "longitude": 2.35521}, {"latitude": 48.87118, "longitude": 2.35529}, {"latitude": 48.87124, "longitude": 2.35532}, {"latitude": 48.87173, "longitude": 2.3556}, {"latitude": 48.87228, "longitude": 2.35591}, {"latitude": 48.87276, "longitude": 2.35617}, {"latitude": 48.87336, "longitude": 2.35651}, {"latitude": 48.87382, "longitude": 2.35676}, {"latitude": 48.87405, "longitude": 2.3569}, {"latitude": 48.8744, "longitude": 2.35711}, {"latitude": 48.87452, "longitude": 2.35718}, {"latitude": 48.87481, "longitude": 2.35734}, {"latitude": 48.87485, "longitude": 2.35737}, {"latitude": 48.87492, "longitude": 2.3573}, {"latitude": 48.87513, "longitude": 2.35711}, {"latitude": 48.87545, "longitude": 2.35684}, {"latitude": 48.87554, "longitude": 2.35676}, {"latitude": 48.87561, "longitude": 2.35671}, {"latitude": 48.87566, "longitude": 2.35667}, {"latitude": 48.87575, "longitude": 2.35661}, {"latitude": 48.87579, "longitude": 2.35658}, {"latitude": 48.87587, "longitude": 2.3565}, {"latitude": 48.87595, "longitude": 2.35642}, {"latitude": 48.876, "longitude": 2.35637}, {"latitude": 48.87603, "longitude": 2.35634}, {"latitude": 48.87622, "longitude": 2.35616}, {"latitude": 48.8763, "longitude": 2.3561}, {"latitude": 48.87637, "longitude": 2.35604}, {"latitude": 48.87649, "longitude": 2.35594}, {"latitude": 48.87654, "longitude": 2.35591}, {"latitude": 48.87658, "longitude": 2.35589}, {"latitude": 48.8766, "longitude": 2.35586}, {"latitude": 48.87675, "longitude": 2.35574}, {"latitude": 48.87677, "longitude": 2.35567}, {"latitude": 48.87709, "longitude": 2.35536}, {"latitude": 48.87717, "longitude": 2.35529}, {"latitude": 48.87733, "longitude": 2.35513}, {"latitude": 48.87741, "longitude": 2.35506}, {"latitude": 48.87771, "longitude": 2.35476}, {"latitude": 48.8778, "longitude": 2.35476}, {"latitude": 48.87814, "longitude": 2.35447}, {"latitude": 48.87818, "longitude": 2.35444}, {"latitude": 48.87834, "longitude": 2.3543}, {"latitude": 48.87846, "longitude": 2.3542}, {"latitude": 48.87855, "longitude": 2.35412}, {"latitude": 48.87872, "longitude": 2.35395}, {"latitude": 48.87894, "longitude": 2.35375}, {"latitude": 48.87933, "longitude": 2.35339}, {"latitude": 48.87947, "longitude": 2.35327}, {"latitude": 48.87992, "longitude": 2.35285}, {"latitude": 48.88027, "longitude": 2.35253}, {"latitude": 48.8803, "longitude": 2.35245}, {"latitude": 48.88036, "longitude": 2.35239}, {"latitude": 48.88042, "longitude": 2.35234}, {"latitude": 48.88049, "longitude": 2.35228}, {"latitude": 48.88062, "longitude": 2.35217}, {"latitude": 48.88103, "longitude": 2.3518}, {"latitude": 48.88125, "longitude": 2.35161}, {"latitude": 48.88145, "longitude": 2.35144}, {"latitude": 48.88181, "longitude": 2.35112}, {"latitude": 48.88187, "longitude": 2.35107}, {"latitude": 48.88195, "longitude": 2.35101}, {"latitude": 48.88317, "longitude": 2.34988}, {"latitude": 48.88337, "longitude": 2.34968}, {"latitude": 48.88349, "longitude": 2.34959}, {"latitude": 48.88353, "longitude": 2.34955}, {"latitude": 48.88361, "longitude": 2.34954}, {"latitude": 48.88362, "longitude": 2.34974}, {"latitude": 48.8837, "longitude": 2.35083}, {"latitude": 48.88373, "longitude": 2.35107}, {"latitude": 48.88375, "longitude": 2.35128}, {"latitude": 48.88378, "longitude": 2.35191}, {"latitude": 48.8838, "longitude": 2.35218}, {"latitude": 48.88381, "longitude": 2.35242}, {"latitude": 48.88388, "longitude": 2.35324}, {"latitude": 48.88395, "longitude": 2.35412}, {"latitude": 48.88402, "longitude": 2.35525}, {"latitude": 48.88405, "longitude": 2.35554}, {"latitude": 48.88406, "longitude": 2.35572}, {"latitude": 48.88408, "longitude": 2.35607}, {"latitude": 48.88411, "longitude": 2.35654}, {"latitude": 48.88414, "longitude": 2.35689}, {"latitude": 48.88417, "longitude": 2.35726}, {"latitude": 48.88423, "longitude": 2.35781}, {"latitude": 48.88428, "longitude": 2.35835}, {"latitude": 48.8843, "longitude": 2.35888}, {"latitude": 48.8843, "longitude": 2.35922}, {"latitude": 48.8843, "longitude": 2.35936}, {"latitude": 48.88443, "longitude": 2.35937}, {"latitude": 48.88452, "longitude": 2.35938}, {"latitude": 48.88465, "longitude": 2.35939}, {"latitude": 48.88478, "longitude": 2.35942}, {"latitude": 48.8849, "longitude": 2.35943}, {"latitude": 48.88523, "longitude": 2.35945}, {"latitude": 48.88571, "longitude": 2.3595}, {"latitude": 48.8861, "longitude": 2.35956}, {"latitude": 48.88667, "longitude": 2.35967}, {"latitude": 48.88682, "longitude": 2.35971}, {"latitude": 48.8872, "longitude": 2.35982}, {"latitude": 48.88748, "longitude": 2.35986}, {"latitude": 48.88783, "longitude": 2.3599}, {"latitude": 48.88802, "longitude": 2.35993}, {"latitude": 48.88806, "longitude": 2.35993}, {"latitude": 48.88905, "longitude": 2.35998}, {"latitude": 48.88914, "longitude": 2.35998}, {"latitude": 48.88916, "longitude": 2.35998}, {"latitude": 48.88979, "longitude": 2.35996}, {"latitude": 48.89024, "longitude": 2.35996}, {"latitude": 48.89045, "longitude": 2.35994}, {"latitude": 48.89055, "longitude": 2.35994}, {"latitude": 48.89084, "longitude": 2.35993}, {"latitude": 48.89105, "longitude": 2.35992}, {"latitude": 48.89154, "longitude": 2.35992}, {"latitude": 48.89201, "longitude": 2.35989}, {"latitude": 48.89212, "longitude": 2.35988}, {"latitude": 48.8927, "longitude": 2.35979}, {"latitude": 48.89332, "longitude": 2.35968}, {"latitude": 48.89355, "longitude": 2.35963}, {"latitude": 48.89362, "longitude": 2.35961}, {"latitude": 48.8943, "longitude": 2.35949}, {"latitude": 48.89452, "longitude": 2.35945}, {"latitude": 48.89495, "longitude": 2.3594}, {"latitude": 48.89508, "longitude": 2.3594}, {"latitude": 48.89516, "longitude": 2.35941}, {"latitude": 48.89525, "longitude": 2.35941}, {"latitude": 48.89533, "longitude": 2.3594}, {"latitude": 48.89548, "longitude": 2.35939}, {"latitude": 48.89572, "longitude": 2.35939}, {"latitude": 48.89577, "longitude": 2.35934}, {"latitude": 48.89597, "longitude": 2.35931}, {"latitude": 48.8961, "longitude": 2.35928}, {"latitude": 48.89623, "longitude": 2.35927}, {"latitude": 48.89699, "longitude": 2.35922}, {"latitude": 48.89711, "longitude": 2.35921}, {"latitude": 48.89756, "longitude": 2.35917}, {"latitude": 48.89772, "longitude": 2.35917}, {"latitude": 48.8978, "longitude": 2.35923}, {"latitude": 48.89819, "longitude": 2.35927}, {"latitude": 48.89834, "longitude": 2.35928}, {"latitude": 48.89857, "longitude": 2.35931}, {"latitude": 48.89864, "longitude": 2.35933}, {"latitude": 48.89871, "longitude": 2.35933}, {"latitude": 48.89885, "longitude": 2.35931}, {"latitude": 48.89893, "longitude": 2.35932}, {"latitude": 48.89913, "longitude": 2.35931}, {"latitude": 48.89923, "longitude": 2.35931}, {"latitude": 48.89939, "longitude": 2.35932}, {"latitude": 48.89953, "longitude": 2.35934}, {"latitude": 48.89962, "longitude": 2.35934}, {"latitude": 48.89997, "longitude": 2.3594}, {"latitude": 48.90019, "longitude": 2.3594}, {"latitude": 48.90026, "longitude": 2.35942}, {"latitude": 48.90036, "longitude": 2.35942}, {"latitude": 48.90051, "longitude": 2.35943}, {"latitude": 48.90077, "longitude": 2.35941}, {"latitude": 48.90094, "longitude": 2.3594}, {"latitude": 48.9011, "longitude": 2.3594}, {"latitude": 48.90147, "longitude": 2.35917}, {"latitude": 48.90155, "longitude": 2.35913}, {"latitude": 48.90159, "longitude": 2.35912}, {"latitude": 48.90162, "longitude": 2.3591}, {"latitude": 48.90175, "longitude": 2.35902}, {"latitude": 48.90195, "longitude": 2.3589}, {"latitude": 48.90229, "longitude": 2.35885}, {"latitude": 48.90261, "longitude": 2.35882}, {"latitude": 48.90313, "longitude": 2.35879}, {"latitude": 48.90375, "longitude": 2.35874}, {"latitude": 48.90517, "longitude": 2.35866}, {"latitude": 48.90541, "longitude": 2.35863}, {"latitude": 48.90576, "longitude": 2.35861}, {"latitude": 48.90601, "longitude": 2.35859}, {"latitude": 48.90614, "longitude": 2.35858}, {"latitude": 48.90653, "longitude": 2.35854}, {"latitude": 48.90818, "longitude": 2.35838}, {"latitude": 48.90889, "longitude": 2.35833}, {"latitude": 48.90949, "longitude": 2.3583}, {"latitude": 48.9099, "longitude": 2.35826}, {"latitude": 48.91016, "longitude": 2.35824}, {"latitude": 48.91049, "longitude": 2.35821}, {"latitude": 48.91071, "longitude": 2.3582}, {"latitude": 48.91094, "longitude": 2.35818}, {"latitude": 48.91113, "longitude": 2.35816}, {"latitude": 48.91132, "longitude": 2.35814}, {"latitude": 48.91177, "longitude": 2.35811}, {"latitude": 48.91227, "longitude": 2.35806}, {"latitude": 48.91266, "longitude": 2.35803}, {"latitude": 48.91294, "longitude": 2.35801}, {"latitude": 48.91323, "longitude": 2.35799}, {"latitude": 48.91375, "longitude": 2.35795}, {"latitude": 48.91508, "longitude": 2.35785}, {"latitude": 48.91521, "longitude": 2.35781}, {"latitude": 48.91543, "longitude": 2.35778}, {"latitude": 48.91552, "longitude": 2.35778}, {"latitude": 48.91601, "longitude": 2.35777}, {"latitude": 48.9172, "longitude": 2.35769}, {"latitude": 48.91814, "longitude": 2.3576}, {"latitude": 48.91847, "longitude": 2.35757}, {"latitude": 48.91875, "longitude": 2.35754}, {"latitude": 48.91975, "longitude": 2.35748}, {"latitude": 48.92154, "longitude": 2.35733}, {"latitude": 48.92219, "longitude": 2.35726}, {"latitude": 48.92238, "longitude": 2.35725}, {"latitude": 48.92254, "longitude": 2.35723}, {"latitude": 48.9227, "longitude": 2.35722}, {"latitude": 48.92414, "longitude": 2.35711}, {"latitude": 48.92509, "longitude": 2.35704}, {"latitude": 48.92572, "longitude": 2.357}, {"latitude": 48.92581, "longitude": 2.35699}, {"latitude": 48.926, "longitude": 2.35698}, {"latitude": 48.92611, "longitude": 2.35696}, {"latitude": 48.92624, "longitude": 2.35696}, {"latitude": 48.92678, "longitude": 2.357}, {"latitude": 48.92698, "longitude": 2.35707}, {"latitude": 48.92707, "longitude": 2.3571}, {"latitude": 48.92716, "longitude": 2.35713}, {"latitude": 48.92734, "longitude": 2.35723}, {"latitude": 48.9275, "longitude": 2.35733}, {"latitude": 48.92763, "longitude": 2.35744}, {"latitude": 48.92772, "longitude": 2.35751}, {"latitude": 48.92799, "longitude": 2.35776}, {"latitude": 48.92831, "longitude": 2.3582}, {"latitude": 48.92842, "longitude": 2.35838}, {"latitude": 48.92853, "longitude": 2.35861}, {"latitude": 48.92866, "longitude": 2.35891}, {"latitude": 48.92874, "longitude": 2.35914}, {"latitude": 48.92881, "longitude": 2.35936}, {"latitude": 48.92904, "longitude": 2.36035}, {"latitude": 48.9293, "longitude": 2.36152}, {"latitude": 48.92937, "longitude": 2.36182}, {"latitude": 48.92938, "longitude": 2.36188}, {"latitude": 48.92939, "longitude": 2.36193}, {"latitude": 48.92945, "longitude": 2.36217}, {"latitude": 48.92957, "longitude": 2.36267}, {"latitude": 48.92994, "longitude": 2.36411}, {"latitude": 48.93001, "longitude": 2.36437}, {"latitude": 48.93018, "longitude": 2.36504}, {"latitude": 48.93027, "longitude": 2.36542}, {"latitude": 48.93028, "longitude": 2.36549}, {"latitude": 48.9303, "longitude": 2.36557}, {"latitude": 48.93033, "longitude": 2.36572}, {"latitude": 48.93054, "longitude": 2.36644}, {"latitude": 48.9308, "longitude": 2.36736}, {"latitude": 48.93157, "longitude": 2.37012}, {"latitude": 48.93182, "longitude": 2.37108}, {"latitude": 48.93212, "longitude": 2.37239}, {"latitude": 48.93229, "longitude": 2.37305}, {"latitude": 48.93249, "longitude": 2.37381}, {"latitude": 48.9326, "longitude": 2.3743}, {"latitude": 48.93264, "longitude": 2.37452}, {"latitude": 48.93269, "longitude": 2.37476}, {"latitude": 48.93309, "longitude": 2.37672}, {"latitude": 48.93311, "longitude": 2.37679}, {"latitude": 48.93312, "longitude": 2.37687}, {"latitude": 48.93327, "longitude": 2.37767}, {"latitude": 48.93337, "longitude": 2.37839}, {"latitude": 48.93361, "longitude": 2.38012}, {"latitude": 48.93371, "longitude": 2.38131}, {"latitude": 48.93375, "longitude": 2.3818}, {"latitude": 48.93384, "longitude": 2.38337}, {"latitude": 48.93385, "longitude": 2.38367}, {"latitude": 48.93387, "longitude": 2.38454}, {"latitude": 48.93386, "longitude": 2.38506}, {"latitude": 48.93386, "longitude": 2.38511}, {"latitude": 48.93392, "longitude": 2.3869}, {"latitude": 48.93393, "longitude": 2.38712}, {"latitude": 48.93393, "longitude": 2.38722}, {"latitude": 48.93393, "longitude": 2.38768}, {"latitude": 48.93396, "longitude": 2.3885}, {"latitude": 48.93402, "longitude": 2.39031}, {"latitude": 48.93414, "longitude": 2.39387}, {"latitude": 48.93419, "longitude": 2.39478}, {"latitude": 48.93421, "longitude": 2.39502}, {"latitude": 48.93434, "longitude": 2.39636}, {"latitude": 48.93448, "longitude": 2.39766}, {"latitude": 48.93473, "longitude": 2.39928}, {"latitude": 48.93489, "longitude": 2.4002}, {"latitude": 48.93501, "longitude": 2.40084}, {"latitude": 48.93545, "longitude": 2.40287}, {"latitude": 48.93548, "longitude": 2.40304}, {"latitude": 48.93555, "longitude": 2.40331}, {"latitude": 48.93564, "longitude": 2.40368}, {"latitude": 48.93571, "longitude": 2.40395}, {"latitude": 48.93754, "longitude": 2.41185}, {"latitude": 48.93773, "longitude": 2.41267}, {"latitude": 48.93798, "longitude": 2.41373}, {"latitude": 48.93802, "longitude": 2.41388}, {"latitude": 48.93811, "longitude": 2.41429}, {"latitude": 48.93835, "longitude": 2.41533}, {"latitude": 48.9384, "longitude": 2.41557}, {"latitude": 48.93844, "longitude": 2.41572}, {"latitude": 48.93873, "longitude": 2.41697}, {"latitude": 48.93874, "longitude": 2.41699}, {"latitude": 48.93896, "longitude": 2.41796}, {"latitude": 48.93903, "longitude": 2.41824}, {"latitude": 48.93923, "longitude": 2.41918}, {"latitude": 48.93933, "longitude": 2.41963}, {"latitude": 48.93973, "longitude": 2.42137}, {"latitude": 48.94004, "longitude": 2.42268}, {"latitude": 48.94006, "longitude": 2.42278}, {"latitude": 48.94007, "longitude": 2.42282}, {"latitude": 48.94008, "longitude": 2.42287}, {"latitude": 48.94014, "longitude": 2.4231}, {"latitude": 48.94081, "longitude": 2.42595}, {"latitude": 48.94099, "longitude": 2.42673}, {"latitude": 48.94104, "longitude": 2.42693}, {"latitude": 48.94134, "longitude": 2.42822}, {"latitude": 48.94165, "longitude": 2.42961}, {"latitude": 48.94168, "longitude": 2.42969}, {"latitude": 48.94221, "longitude": 2.43172}, {"latitude": 48.9424, "longitude": 2.43245}, {"latitude": 48.94243, "longitude": 2.43254}, {"latitude": 48.94245, "longitude": 2.43263}, {"latitude": 48.94249, "longitude": 2.43277}, {"latitude": 48.94252, "longitude": 2.43292}, {"latitude": 48.94258, "longitude": 2.43312}, {"latitude": 48.94273, "longitude": 2.43361}, {"latitude": 48.94287, "longitude": 2.43405}, {"latitude": 48.94324, "longitude": 2.43506}, {"latitude": 48.94344, "longitude": 2.43557}, {"latitude": 48.94386, "longitude": 2.43663}, {"latitude": 48.94437, "longitude": 2.43777}, {"latitude": 48.94454, "longitude": 2.43814}, {"latitude": 48.94463, "longitude": 2.43832}, {"latitude": 48.94468, "longitude": 2.43843}, {"latitude": 48.94494, "longitude": 2.43896}, {"latitude": 48.94527, "longitude": 2.43966}, {"latitude": 48.94626, "longitude": 2.44153}, {"latitude": 48.94647, "longitude": 2.44194}, {"latitude": 48.94791, "longitude": 2.44458}, {"latitude": 48.94836, "longitude": 2.44544}, {"latitude": 48.9486, "longitude": 2.44587}, {"latitude": 48.94953, "longitude": 2.44758}, {"latitude": 48.95033, "longitude": 2.44901}, {"latitude": 48.95036, "longitude": 2.44909}, {"latitude": 48.95046, "longitude": 2.44928}, {"latitude": 48.95112, "longitude": 2.45052}, {"latitude": 48.9519, "longitude": 2.452}, {"latitude": 48.95424, "longitude": 2.45636}, {"latitude": 48.95508, "longitude": 2.4579}, {"latitude": 48.95517, "longitude": 2.45808}, {"latitude": 48.95526, "longitude": 2.45824}, {"latitude": 48.95544, "longitude": 2.4586}, {"latitude": 48.95587, "longitude": 2.45943}, {"latitude": 48.95623, "longitude": 2.4601}, {"latitude": 48.95667, "longitude": 2.46094}, {"latitude": 48.9572, "longitude": 2.46192}, {"latitude": 48.9576, "longitude": 2.46266}, {"latitude": 48.95808, "longitude": 2.46352}, {"latitude": 48.95889, "longitude": 2.46505}, {"latitude": 48.95992, "longitude": 2.46693}, {"latitude": 48.96031, "longitude": 2.4676}, {"latitude": 48.96089, "longitude": 2.46856}, {"latitude": 48.96106, "longitude": 2.46882}, {"latitude": 48.9611, "longitude": 2.4689}, {"latitude": 48.96116, "longitude": 2.46899}, {"latitude": 48.96119, "longitude": 2.46905}, {"latitude": 48.96196, "longitude": 2.47022}, {"latitude": 48.96288, "longitude": 2.47158}, {"latitude": 48.96296, "longitude": 2.47169}, {"latitude": 48.96321, "longitude": 2.47206}, {"latitude": 48.96385, "longitude": 2.47301}, {"latitude": 48.96462, "longitude": 2.47419}, {"latitude": 48.96593, "longitude": 2.47615}, {"latitude": 48.96635, "longitude": 2.47678}, {"latitude": 48.96636, "longitude": 2.4768}, {"latitude": 48.96678, "longitude": 2.47744}, {"latitude": 48.96691, "longitude": 2.47762}, {"latitude": 48.96705, "longitude": 2.47785}, {"latitude": 48.9676, "longitude": 2.47866}, {"latitude": 48.96772, "longitude": 2.47885}, {"latitude": 48.96811, "longitude": 2.47943}, {"latitude": 48.96919, "longitude": 2.48107}, {"latitude": 48.9695, "longitude": 2.48148}, {"latitude": 48.97043, "longitude": 2.48291}, {"latitude": 48.97111, "longitude": 2.48396}, {"latitude": 48.97404, "longitude": 2.48834}, {"latitude": 48.97413, "longitude": 2.48852}, {"latitude": 48.97416, "longitude": 2.48856}, {"latitude": 48.9742, "longitude": 2.48865}, {"latitude": 48.9766, "longitude": 2.49229}, {"latitude": 48.97696, "longitude": 2.49286}, {"latitude": 48.97705, "longitude": 2.49298}, {"latitude": 48.97856, "longitude": 2.49533}, {"latitude": 48.97941, "longitude": 2.49662}, {"latitude": 48.97989, "longitude": 2.49729}, {"latitude": 48.98188, "longitude": 2.50028}, {"latitude": 48.98289, "longitude": 2.50181}, {"latitude": 48.9831, "longitude": 2.50213}, {"latitude": 48.98418, "longitude": 2.50379}, {"latitude": 48.98462, "longitude": 2.50444}, {"latitude": 48.98494, "longitude": 2.50488}, {"latitude": 48.98539, "longitude": 2.50551}, {"latitude": 48.98644, "longitude": 2.50687}, {"latitude": 48.98711, "longitude": 2.50768}, {"latitude": 48.98736, "longitude": 2.50797}, {"latitude": 48.98882, "longitude": 2.50955}, {"latitude": 48.99053, "longitude": 2.51142}, {"latitude": 48.99077, "longitude": 2.51171}, {"latitude": 48.99151, "longitude": 2.51248}, {"latitude": 48.99194, "longitude": 2.51294}, {"latitude": 48.9941, "longitude": 2.51533}, {"latitude": 48.99425, "longitude": 2.51549}, {"latitude": 48.99431, "longitude": 2.51554}, {"latitude": 48.99435, "longitude": 2.5156}, {"latitude": 48.9944, "longitude": 2.51566}, {"latitude": 48.99447, "longitude": 2.51574}, {"latitude": 48.99626, "longitude": 2.5177}, {"latitude": 48.99746, "longitude": 2.519}, {"latitude": 48.99855, "longitude": 2.52017}, {"latitude": 48.99902, "longitude": 2.52068}, {"latitude": 49.00035, "longitude": 2.52212}, {"latitude": 49.00145, "longitude": 2.5232}, {"latitude": 49.00262, "longitude": 2.52428}, {"latitude": 49.00307, "longitude": 2.52461}, {"latitude": 49.00356, "longitude": 2.52501}, {"latitude": 49.00475, "longitude": 2.52583}, {"latitude": 49.00479, "longitude": 2.52586}, {"latitude": 49.00551, "longitude": 2.52633}, {"latitude": 49.00584, "longitude": 2.52654}, {"latitude": 49.00643, "longitude": 2.52686}, {"latitude": 49.00705, "longitude": 2.52719}, {"latitude": 49.00764, "longitude": 2.5275}, {"latitude": 49.00772, "longitude": 2.52753}, {"latitude": 49.0078, "longitude": 2.52758}, {"latitude": 49.00818, "longitude": 2.52776}, {"latitude": 49.00832, "longitude": 2.52783}, {"latitude": 49.00892, "longitude": 2.52815}, {"latitude": 49.00964, "longitude": 2.5285}, {"latitude": 49.00993, "longitude": 2.52865}, {"latitude": 49.01159, "longitude": 2.52948}, {"latitude": 49.01357, "longitude": 2.53048}, {"latitude": 49.01452, "longitude": 2.53096}, {"latitude": 49.01515, "longitude": 2.53129}, {"latitude": 49.01528, "longitude": 2.53135}, {"latitude": 49.01555, "longitude": 2.5315}, {"latitude": 49.01563, "longitude": 2.53153}, {"latitude": 49.01606, "longitude": 2.53177}, {"latitude": 49.01613, "longitude": 2.5318}, {"latitude": 49.01638, "longitude": 2.53192}, {"latitude": 49.01677, "longitude": 2.53212}, {"latitude": 49.01695, "longitude": 2.5322}, {"latitude": 49.01722, "longitude": 2.53232}, {"latitude": 49.01731, "longitude": 2.53237}, {"latitude": 49.01772, "longitude": 2.53258}, {"latitude": 49.01788, "longitude": 2.53266}, {"latitude": 49.01823, "longitude": 2.53283}, {"latitude": 49.01866, "longitude": 2.53304}, {"latitude": 49.01881, "longitude": 2.53312}, {"latitude": 49.01911, "longitude": 2.53327}, {"latitude": 49.01945, "longitude": 2.53345}, {"latitude": 49.021, "longitude": 2.53426}, {"latitude": 49.02155, "longitude": 2.53455}, {"latitude": 49.02313, "longitude": 2.53533}, {"latitude": 49.02334, "longitude": 2.53541}, {"latitude": 49.02375, "longitude": 2.53562}, {"latitude": 49.02542, "longitude": 2.53648}, {"latitude": 49.02618, "longitude": 2.53686}, {"latitude": 49.02628, "longitude": 2.53692}, {"latitude": 49.02634, "longitude": 2.53695}, {"latitude": 49.02672, "longitude": 2.53714}, {"latitude": 49.0271, "longitude": 2.53734}, {"latitude": 49.02717, "longitude": 2.53737}, {"latitude": 49.02733, "longitude": 2.53744}, {"latitude": 49.02854, "longitude": 2.53805}, {"latitude": 49.02865, "longitude": 2.53811}, {"latitude": 49.02877, "longitude": 2.53817}, {"latitude": 49.02888, "longitude": 2.53823}, {"latitude": 49.02898, "longitude": 2.53827}, {"latitude": 49.02913, "longitude": 2.53835}, {"latitude": 49.03002, "longitude": 2.53879}, {"latitude": 49.03072, "longitude": 2.53914}, {"latitude": 49.03146, "longitude": 2.53948}, {"latitude": 49.03159, "longitude": 2.53954}, {"latitude": 49.03216, "longitude": 2.53982}, {"latitude": 49.03378, "longitude": 2.54041}, {"latitude": 49.03419, "longitude": 2.54057}, {"latitude": 49.03468, "longitude": 2.54074}, {"latitude": 49.03649, "longitude": 2.54141}, {"latitude": 49.03832, "longitude": 2.54206}, {"latitude": 49.0391, "longitude": 2.54235}, {"latitude": 49.03988, "longitude": 2.54265}, {"latitude": 49.04057, "longitude": 2.54291}, {"latitude": 49.04128, "longitude": 2.5432}, {"latitude": 49.04229, "longitude": 2.54367}, {"latitude": 49.04297, "longitude": 2.54405}, {"latitude": 49.0432, "longitude": 2.54419}, {"latitude": 49.04406, "longitude": 2.54471}, {"latitude": 49.04488, "longitude": 2.54525}, {"latitude": 49.04612, "longitude": 2.54601}, {"latitude": 49.04644, "longitude": 2.54619}, {"latitude": 49.04675, "longitude": 2.54636}, {"latitude": 49.04726, "longitude": 2.5466}, {"latitude": 49.04806, "longitude": 2.54697}, {"latitude": 49.04855, "longitude": 2.54716}, {"latitude": 49.04958, "longitude": 2.5475}, {"latitude": 49.05001, "longitude": 2.54762}, {"latitude": 49.05184, "longitude": 2.54808}, {"latitude": 49.05223, "longitude": 2.54815}, {"latitude": 49.05234, "longitude": 2.54817}, {"latitude": 49.05241, "longitude": 2.54819}, {"latitude": 49.05316, "longitude": 2.54839}, {"latitude": 49.05338, "longitude": 2.54843}, {"latitude": 49.05404, "longitude": 2.5486}, {"latitude": 49.05446, "longitude": 2.54873}, {"latitude": 49.05478, "longitude": 2.54883}, {"latitude": 49.05524, "longitude": 2.54897}, {"latitude": 49.05603, "longitude": 2.54926}, {"latitude": 49.05654, "longitude": 2.54947}, {"latitude": 49.05743, "longitude": 2.54993}, {"latitude": 49.0593, "longitude": 2.55088}, {"latitude": 49.05997, "longitude": 2.5512}, {"latitude": 49.06047, "longitude": 2.55143}, {"latitude": 49.06125, "longitude": 2.55176}, {"latitude": 49.06195, "longitude": 2.55201}, {"latitude": 49.06283, "longitude": 2.55227}, {"latitude": 49.06396, "longitude": 2.55251}, {"latitude": 49.06463, "longitude": 2.55263}, {"latitude": 49.06494, "longitude": 2.55267}, {"latitude": 49.06546, "longitude": 2.55273}, {"latitude": 49.06601, "longitude": 2.55275}, {"latitude": 49.06737, "longitude": 2.5527}, {"latitude": 49.06761, "longitude": 2.55269}, {"latitude": 49.06822, "longitude": 2.55265}, {"latitude": 49.06857, "longitude": 2.55263}, {"latitude": 49.0702, "longitude": 2.55249}, {"latitude": 49.07131, "longitude": 2.55241}, {"latitude": 49.07219, "longitude": 2.55231}, {"latitude": 49.07391, "longitude": 2.55218}, {"latitude": 49.07543, "longitude": 2.55203}, {"latitude": 49.07555, "longitude": 2.55202}, {"latitude": 49.07579, "longitude": 2.55199}, {"latitude": 49.0759, "longitude": 2.55198}, {"latitude": 49.07719, "longitude": 2.55188}, {"latitude": 49.07917, "longitude": 2.55171}, {"latitude": 49.07949, "longitude": 2.5517}, {"latitude": 49.08136, "longitude": 2.55154}, {"latitude": 49.08164, "longitude": 2.55151}, {"latitude": 49.0832, "longitude": 2.55137}, {"latitude": 49.08639, "longitude": 2.55111}, {"latitude": 49.08647, "longitude": 2.55111}, {"latitude": 49.08691, "longitude": 2.55107}, {"latitude": 49.08835, "longitude": 2.55093}, {"latitude": 49.08856, "longitude": 2.55094}, {"latitude": 49.08929, "longitude": 2.55088}, {"latitude": 49.08966, "longitude": 2.55086}, {"latitude": 49.08979, "longitude": 2.55084}, {"latitude": 49.09167, "longitude": 2.55065}, {"latitude": 49.09182, "longitude": 2.55063}, {"latitude": 49.09417, "longitude": 2.55045}, {"latitude": 49.09529, "longitude": 2.55035}, {"latitude": 49.09573, "longitude": 2.55031}, {"latitude": 49.09629, "longitude": 2.55027}, {"latitude": 49.09705, "longitude": 2.55023}, {"latitude": 49.09815, "longitude": 2.55023}, {"latitude": 49.09869, "longitude": 2.55026}, {"latitude": 49.09961, "longitude": 2.55036}, {"latitude": 49.10009, "longitude": 2.55043}, {"latitude": 49.10124, "longitude": 2.55063}, {"latitude": 49.10159, "longitude": 2.55068}, {"latitude": 49.10195, "longitude": 2.55074}, {"latitude": 49.10219, "longitude": 2.55078}, {"latitude": 49.10232, "longitude": 2.5508}, {"latitude": 49.10745, "longitude": 2.55164}, {"latitude": 49.10771, "longitude": 2.5517}, {"latitude": 49.10885, "longitude": 2.55194}, {"latitude": 49.10889, "longitude": 2.55195}, {"latitude": 49.10989, "longitude": 2.55225}, {"latitude": 49.1111, "longitude": 2.55269}, {"latitude": 49.11202, "longitude": 2.55308}, {"latitude": 49.11286, "longitude": 2.55349}, {"latitude": 49.11477, "longitude": 2.55449}, {"latitude": 49.11602, "longitude": 2.55513}, {"latitude": 49.11674, "longitude": 2.55546}, {"latitude": 49.11821, "longitude": 2.5561}, {"latitude": 49.11907, "longitude": 2.55637}, {"latitude": 49.12022, "longitude": 2.55663}, {"latitude": 49.12109, "longitude": 2.55679}, {"latitude": 49.12197, "longitude": 2.5569}, {"latitude": 49.12231, "longitude": 2.55696}, {"latitude": 49.12329, "longitude": 2.55704}, {"latitude": 49.12344, "longitude": 2.55705}, {"latitude": 49.12359, "longitude": 2.55707}, {"latitude": 49.12498, "longitude": 2.55728}, {"latitude": 49.12552, "longitude": 2.55738}, {"latitude": 49.12687, "longitude": 2.55776}, {"latitude": 49.12731, "longitude": 2.5579}, {"latitude": 49.12789, "longitude": 2.55812}, {"latitude": 49.12862, "longitude": 2.55847}, {"latitude": 49.12907, "longitude": 2.5587}, {"latitude": 49.12968, "longitude": 2.55904}, {"latitude": 49.13057, "longitude": 2.55965}, {"latitude": 49.13086, "longitude": 2.55985}, {"latitude": 49.13113, "longitude": 2.56005}, {"latitude": 49.13159, "longitude": 2.56042}, {"latitude": 49.13228, "longitude": 2.56102}, {"latitude": 49.13292, "longitude": 2.56162}, {"latitude": 49.13366, "longitude": 2.56242}, {"latitude": 49.13372, "longitude": 2.56248}, {"latitude": 49.13419, "longitude": 2.56301}, {"latitude": 49.13476, "longitude": 2.56371}, {"latitude": 49.13553, "longitude": 2.56468}, {"latitude": 49.13702, "longitude": 2.56658}, {"latitude": 49.13913, "longitude": 2.56925}, {"latitude": 49.14034, "longitude": 2.5708}, {"latitude": 49.14078, "longitude": 2.57136}, {"latitude": 49.14248, "longitude": 2.57352}, {"latitude": 49.14274, "longitude": 2.57386}, {"latitude": 49.14503, "longitude": 2.57678}, {"latitude": 49.14543, "longitude": 2.57726}, {"latitude": 49.14783, "longitude": 2.58036}, {"latitude": 49.14851, "longitude": 2.58121}, {"latitude": 49.14872, "longitude": 2.58147}, {"latitude": 49.15283, "longitude": 2.58662}, {"latitude": 49.15508, "longitude": 2.58943}, {"latitude": 49.15645, "longitude": 2.5912}, {"latitude": 49.15685, "longitude": 2.59171}, {"latitude": 49.15768, "longitude": 2.59277}, {"latitude": 49.15769, "longitude": 2.59277}, {"latitude": 49.15944, "longitude": 2.59498}, {"latitude": 49.15986, "longitude": 2.59548}, {"latitude": 49.16077, "longitude": 2.59641}, {"latitude": 49.16128, "longitude": 2.59688}, {"latitude": 49.16231, "longitude": 2.59766}, {"latitude": 49.16346, "longitude": 2.59838}, {"latitude": 49.16405, "longitude": 2.59864}, {"latitude": 49.16449, "longitude": 2.59883}, {"latitude": 49.16506, "longitude": 2.59905}, {"latitude": 49.16561, "longitude": 2.59922}, {"latitude": 49.16586, "longitude": 2.5993}, {"latitude": 49.16602, "longitude": 2.59933}, {"latitude": 49.16642, "longitude": 2.59941}, {"latitude": 49.16714, "longitude": 2.59951}, {"latitude": 49.16812, "longitude": 2.59954}, {"latitude": 49.16971, "longitude": 2.59955}, {"latitude": 49.17047, "longitude": 2.59961}, {"latitude": 49.171, "longitude": 2.59972}, {"latitude": 49.17167, "longitude": 2.59987}, {"latitude": 49.17203, "longitude": 2.59997}, {"latitude": 49.17238, "longitude": 2.6001}, {"latitude": 49.1728, "longitude": 2.60025}, {"latitude": 49.17308, "longitude": 2.60038}, {"latitude": 49.17349, "longitude": 2.60059}, {"latitude": 49.17414, "longitude": 2.60094}, {"latitude": 49.17419, "longitude": 2.60098}, {"latitude": 49.17469, "longitude": 2.60131}, {"latitude": 49.1748, "longitude": 2.60138}, {"latitude": 49.17528, "longitude": 2.6017}, {"latitude": 49.17641, "longitude": 2.60264}, {"latitude": 49.17663, "longitude": 2.60281}, {"latitude": 49.17684, "longitude": 2.60298}, {"latitude": 49.17732, "longitude": 2.60337}, {"latitude": 49.17752, "longitude": 2.60349}, {"latitude": 49.17806, "longitude": 2.60387}, {"latitude": 49.17847, "longitude": 2.60413}, {"latitude": 49.1791, "longitude": 2.60449}, {"latitude": 49.17946, "longitude": 2.60466}, {"latitude": 49.18004, "longitude": 2.60491}, {"latitude": 49.18077, "longitude": 2.60516}, {"latitude": 49.18149, "longitude": 2.60534}, {"latitude": 49.1822, "longitude": 2.60546}, {"latitude": 49.1829, "longitude": 2.60552}, {"latitude": 49.18332, "longitude": 2.60554}, {"latitude": 49.18374, "longitude": 2.60553}, {"latitude": 49.18449, "longitude": 2.60546}, {"latitude": 49.18525, "longitude": 2.60534}, {"latitude": 49.18578, "longitude": 2.60521}, {"latitude": 49.1862, "longitude": 2.60508}, {"latitude": 49.18702, "longitude": 2.60478}, {"latitude": 49.18946, "longitude": 2.60379}, {"latitude": 49.18973, "longitude": 2.60371}, {"latitude": 49.19013, "longitude": 2.60361}, {"latitude": 49.19107, "longitude": 2.60345}, {"latitude": 49.1918, "longitude": 2.60338}, {"latitude": 49.1926, "longitude": 2.60339}, {"latitude": 49.19357, "longitude": 2.6035}, {"latitude": 49.19402, "longitude": 2.60361}, {"latitude": 49.19493, "longitude": 2.60387}, {"latitude": 49.19504, "longitude": 2.60391}, {"latitude": 49.19525, "longitude": 2.60399}, {"latitude": 49.19549, "longitude": 2.60408}, {"latitude": 49.19596, "longitude": 2.6043}, {"latitude": 49.19607, "longitude": 2.60436}, {"latitude": 49.19653, "longitude": 2.60461}, {"latitude": 49.19668, "longitude": 2.60469}, {"latitude": 49.19678, "longitude": 2.60475}, {"latitude": 49.19735, "longitude": 2.60511}, {"latitude": 49.19753, "longitude": 2.60523}, {"latitude": 49.19771, "longitude": 2.60536}, {"latitude": 49.19844, "longitude": 2.60587}, {"latitude": 49.19943, "longitude": 2.60657}, {"latitude": 49.20206, "longitude": 2.60843}, {"latitude": 49.20287, "longitude": 2.60901}, {"latitude": 49.20338, "longitude": 2.60938}, {"latitude": 49.20461, "longitude": 2.61037}, {"latitude": 49.2054, "longitude": 2.61098}, {"latitude": 49.20544, "longitude": 2.61109}, {"latitude": 49.20546, "longitude": 2.61114}, {"latitude": 49.20549, "longitude": 2.61117}, {"latitude": 49.20553, "longitude": 2.61121}, {"latitude": 49.20558, "longitude": 2.61125}, {"latitude": 49.20571, "longitude": 2.6114}, {"latitude": 49.20591, "longitude": 2.61162}, {"latitude": 49.206, "longitude": 2.61174}, {"latitude": 49.20609, "longitude": 2.61189}, {"latitude": 49.20614, "longitude": 2.61203}, {"latitude": 49.20618, "longitude": 2.61221}, {"latitude": 49.20617, "longitude": 2.6124}, {"latitude": 49.20614, "longitude": 2.61257}, {"latitude": 49.20608, "longitude": 2.61272}, {"latitude": 49.20601, "longitude": 2.61283}, {"latitude": 49.20593, "longitude": 2.61291}, {"latitude": 49.20587, "longitude": 2.61295}, {"latitude": 49.20582, "longitude": 2.61297}, {"latitude": 49.20574, "longitude": 2.61298}, {"latitude": 49.20568, "longitude": 2.61298}, {"latitude": 49.20561, "longitude": 2.61296}, {"latitude": 49.20555, "longitude": 2.61292}, {"latitude": 49.20549, "longitude": 2.61287}, {"latitude": 49.20538, "longitude": 2.61273}, {"latitude": 49.20531, "longitude": 2.61254}, {"latitude": 49.20529, "longitude": 2.61242}, {"latitude": 49.20528, "longitude": 2.61233}, {"latitude": 49.20527, "longitude": 2.61222}, {"latitude": 49.2053, "longitude": 2.61203}, {"latitude": 49.2054, "longitude": 2.61173}, {"latitude": 49.20545, "longitude": 2.61159}, {"latitude": 49.20558, "longitude": 2.61125}, {"latitude": 49.20562, "longitude": 2.61115}, {"latitude": 49.20567, "longitude": 2.61098}, {"latitude": 49.20583, "longitude": 2.61056}, {"latitude": 49.20592, "longitude": 2.61036}, {"latitude": 49.206, "longitude": 2.61023}, {"latitude": 49.20607, "longitude": 2.61015}, {"latitude": 49.20614, "longitude": 2.61008}, {"latitude": 49.20642, "longitude": 2.60993}, {"latitude": 49.20671, "longitude": 2.60979}, {"latitude": 49.20681, "longitude": 2.60973}, {"latitude": 49.20719, "longitude": 2.60953}, {"latitude": 49.20743, "longitude": 2.6094}, {"latitude": 49.20757, "longitude": 2.60932}, {"latitude": 49.20796, "longitude": 2.60911}, {"latitude": 49.20808, "longitude": 2.60904}, {"latitude": 49.20843, "longitude": 2.60883}, {"latitude": 49.20857, "longitude": 2.60876}, {"latitude": 49.20869, "longitude": 2.60869}, {"latitude": 49.20877, "longitude": 2.60859}, {"latitude": 49.20906, "longitude": 2.60844}, {"latitude": 49.20927, "longitude": 2.60839}, {"latitude": 49.20933, "longitude": 2.60838}, {"latitude": 49.20968, "longitude": 2.60824}, {"latitude": 49.20989, "longitude": 2.60814}, {"latitude": 49.20998, "longitude": 2.60813}, {"latitude": 49.21006, "longitude": 2.60813}, {"latitude": 49.21014, "longitude": 2.60816}, {"latitude": 49.21025, "longitude": 2.60822}, {"latitude": 49.2103, "longitude": 2.60826}, {"latitude": 49.21032, "longitude": 2.60828}, {"latitude": 49.21043, "longitude": 2.60842}, {"latitude": 49.21048, "longitude": 2.60852}, {"latitude": 49.21052, "longitude": 2.60862}, {"latitude": 49.21055, "longitude": 2.60874}, {"latitude": 49.21056, "longitude": 2.60885}, {"latitude": 49.21057, "longitude": 2.60901}, {"latitude": 49.21056, "longitude": 2.60915}, {"latitude": 49.21055, "longitude": 2.60921}, {"latitude": 49.21051, "longitude": 2.60935}, {"latitude": 49.21048, "longitude": 2.60942}, {"latitude": 49.21045, "longitude": 2.60949}, {"latitude": 49.21041, "longitude": 2.60956}, {"latitude": 49.21036, "longitude": 2.60963}, {"latitude": 49.21031, "longitude": 2.60967}, {"latitude": 49.21026, "longitude": 2.60972}, {"latitude": 49.2102, "longitude": 2.60975}, {"latitude": 49.21019, "longitude": 2.60976}, {"latitude": 49.21009, "longitude": 2.60979}, {"latitude": 49.20997, "longitude": 2.60979}, {"latitude": 49.20985, "longitude": 2.60975}, {"latitude": 49.20978, "longitude": 2.60972}, {"latitude": 49.20963, "longitude": 2.60963}, {"latitude": 49.20963, "longitude": 2.60958}, {"latitude": 49.20961, "longitude": 2.60955}, {"latitude": 49.20959, "longitude": 2.6095}, {"latitude": 49.20958, "longitude": 2.60948}, {"latitude": 49.20955, "longitude": 2.60946}, {"latitude": 49.20953, "longitude": 2.60944}, {"latitude": 49.2095, "longitude": 2.60942}, {"latitude": 49.20947, "longitude": 2.60934}, {"latitude": 49.20945, "longitude": 2.60928}, {"latitude": 49.20943, "longitude": 2.60913}, {"latitude": 49.20941, "longitude": 2.60897}, {"latitude": 49.20937, "longitude": 2.60865}, {"latitude": 49.20933, "longitude": 2.60838}, {"latitude": 49.20932, "longitude": 2.60831}, {"latitude": 49.20921, "longitude": 2.60731}, {"latitude": 49.20913, "longitude": 2.6066}, {"latitude": 49.20912, "longitude": 2.60644}, {"latitude": 49.20909, "longitude": 2.6062}, {"latitude": 49.20902, "longitude": 2.60555}, {"latitude": 49.20883, "longitude": 2.60384}, {"latitude": 49.2087, "longitude": 2.60254}, {"latitude": 49.20869, "longitude": 2.60249}, {"latitude": 49.20869, "longitude": 2.60247}, {"latitude": 49.20865, "longitude": 2.60208}, {"latitude": 49.20864, "longitude": 2.60195}, {"latitude": 49.20862, "longitude": 2.60179}, {"latitude": 49.2086, "longitude": 2.60164}, {"latitude": 49.20851, "longitude": 2.60081}, {"latitude": 49.20836, "longitude": 2.59938}, {"latitude": 49.20821, "longitude": 2.59802}, {"latitude": 49.20819, "longitude": 2.59778}, {"latitude": 49.20814, "longitude": 2.59732}, {"latitude": 49.20809, "longitude": 2.59691}, {"latitude": 49.20806, "longitude": 2.59667}, {"latitude": 49.20803, "longitude": 2.59643}, {"latitude": 49.20795, "longitude": 2.59562}, {"latitude": 49.20789, "longitude": 2.59501}, {"latitude": 49.20786, "longitude": 2.59497}, {"latitude": 49.20772, "longitude": 2.59353}, {"latitude": 49.20769, "longitude": 2.59325}, {"latitude": 49.20767, "longitude": 2.59313}, {"latitude": 49.20763, "longitude": 2.59277}, {"latitude": 49.20761, "longitude": 2.59252}, {"latitude": 49.2076, "longitude": 2.59234}, {"latitude": 49.2076, "longitude": 2.59229}, {"latitude": 49.20761, "longitude": 2.59224}, {"latitude": 49.20762, "longitude": 2.59218}, {"latitude": 49.20765, "longitude": 2.59205}, {"latitude": 49.20782, "longitude": 2.59157}, {"latitude": 49.20811, "longitude": 2.59073}, {"latitude": 49.20796, "longitude": 2.5906}, {"latitude": 49.20781, "longitude": 2.5905}, {"latitude": 49.20758, "longitude": 2.59032}, {"latitude": 49.20737, "longitude": 2.59017}, {"latitude": 49.20711, "longitude": 2.58998}, {"latitude": 49.20706, "longitude": 2.5899}, {"latitude": 49.20696, "longitude": 2.58983}, {"latitude": 49.2068, "longitude": 2.58971}, {"latitude": 49.20671, "longitude": 2.58964}, {"latitude": 49.20656, "longitude": 2.58952}, {"latitude": 49.20655, "longitude": 2.58948}, {"latitude": 49.20654, "longitude": 2.58944}, {"latitude": 49.20652, "longitude": 2.58941}, {"latitude": 49.20649, "longitude": 2.58939}, {"latitude": 49.20647, "longitude": 2.58939}, {"latitude": 49.20644, "longitude": 2.58939}, {"latitude": 49.20642, "longitude": 2.58941}, {"latitude": 49.2064, "longitude": 2.58944}, {"latitude": 49.20639, "longitude": 2.58948}, {"latitude": 49.20629, "longitude": 2.58941}, {"latitude": 49.20617, "longitude": 2.58929}, {"latitude": 49.20613, "longitude": 2.58924}, {"latitude": 49.20605, "longitude": 2.58912}, {"latitude": 49.20574, "longitude": 2.58859}, {"latitude": 49.20559, "longitude": 2.58836}, {"latitude": 49.20503, "longitude": 2.58747}, {"latitude": 49.2049, "longitude": 2.58728}, {"latitude": 49.20473, "longitude": 2.587}, {"latitude": 49.20448, "longitude": 2.58661}, {"latitude": 49.20426, "longitude": 2.58626}, {"latitude": 49.20423, "longitude": 2.58621}]}], "sections": [{"startPointIndex": 0, "endPointIndex": 388, "sectionType": "URBAN"}, {"startPointIndex": 390, "endPointIndex": 419, "sectionType": "URBAN"}, {"startPointIndex": 433, "endPointIndex": 501, "sectionType": "URBAN"}, {"startPointIndex": 536, "endPointIndex": 537, "sectionType": "URBAN"}, {"startPointIndex": 209, "endPointIndex": 741, "sectionType": "MOTORWAY"}, {"startPointIndex": 783, "endPointIndex": 790, "sectionType": "URBAN"}, {"startPointIndex": 841, "endPointIndex": 906, "sectionType": "URBAN"}]}]}